MANIFEST.in
README.rst
setup.py
SQLAntaresia.egg-info/PKG-INFO
SQLAntaresia.egg-info/SOURCES.txt
SQLAntaresia.egg-info/dependency_links.txt
SQLAntaresia.egg-info/top_level.txt
bin/sqlantaresia
sqlantaresia/ConfigureConnection.py
sqlantaresia/ConfigureConnectionDialog.ui
sqlantaresia/ProcessListTab.py
sqlantaresia/ProcessListWidget.ui
sqlantaresia/QMiddleClickCloseTabBar.py
sqlantaresia/QPySqlModels.py
sqlantaresia/QueryTab.py
sqlantaresia/QueryWidget.ui
sqlantaresia/SQLAntaresia.py
sqlantaresia/SQLAntaresiaWindow.ui
sqlantaresia/SettingsDialog.py
sqlantaresia/SettingsDialog.ui
sqlantaresia/TableDetails.py
sqlantaresia/TableDetailsWidget.ui
sqlantaresia/Ui_ConfigureConnectionDialog.py
sqlantaresia/Ui_DBTabContainer.py
sqlantaresia/Ui_ProcessListWidget.py
sqlantaresia/Ui_QueryWidget.py
sqlantaresia/Ui_SQLAntaresiaWindow.py
sqlantaresia/Ui_SettingsDialog.py
sqlantaresia/Ui_Tab.py
sqlantaresia/Ui_TableDetailsWidget.py
sqlantaresia/__init__.py
sqlantaresia/application.py
sqlantaresia/connections.py
sqlantaresia/dbmodels.py
sqlantaresia/icons_rc.py
sqlantaresia/icons/application-exit.png
sqlantaresia/icons/configure.png
sqlantaresia/icons/control_panel.png
sqlantaresia/icons/database.png
sqlantaresia/icons/database_connect.png
sqlantaresia/icons/database_edit.png
sqlantaresia/icons/database_refresh.png
sqlantaresia/icons/database_server.png
sqlantaresia/icons/database_table.png
sqlantaresia/icons/dialog-ok-apply.png
sqlantaresia/icons/document-properties.png
sqlantaresia/icons/edit-delete.png
sqlantaresia/icons/edit-undo.png
sqlantaresia/icons/group.png
sqlantaresia/icons/layer_database.png
sqlantaresia/icons/list-add.png
sqlantaresia/icons/list-remove.png
sqlantaresia/icons/network-connect.png
sqlantaresia/icons/network-disconnect.png
sqlantaresia/icons/qtlogo.png
sqlantaresia/icons/server-database.png
sqlantaresia/icons/system-run.png
sqlantaresia/icons/tab-close.png
sqlantaresia/icons/tab-new.png
sqlantaresia/icons/user.png
sqlantaresia/icons/view-refresh.png