Metadata-Version: 1.1
Name: SQLAntaresia
Version: 0.4.1
Summary: Cross platform MySQL management tools aimed at both developers and system administrators
Home-page: http://github.com/mtorromeo/sqlantaresia
Author: Massimiliano Torromeo
Author-email: massimiliano.torromeo@gmail.com
License: MIT License
Download-URL: http://github.com/mtorromeo/sqlantaresia/tarball/v0.4.1
Keywords: qt,pyqt,desktop,mysql
Platform: UNKNOWN
Classifier: Programming Language :: Python
Classifier: Programming Language :: Python :: 2.6
Classifier: Programming Language :: Python :: 2.7
Classifier: License :: OSI Approved :: MIT License
Classifier: Environment :: X11 Applications :: Qt
Classifier: Intended Audience :: System Administrators
Classifier: Operating System :: MacOS :: MacOS X
Classifier: Operating System :: Microsoft :: Windows
Classifier: Operating System :: POSIX :: Linux
Classifier: Operating System :: POSIX :: BSD
Classifier: Natural Language :: English
Classifier: Topic :: Utilities
Requires: paramiko
Requires: MySQL_python
Requires: DBUtils
Requires: setproctitle
